cdk_prowler/__init__.py
cdk_prowler/py.typed
cdk_prowler/_jsii/__init__.py
cdk_prowler/_jsii/cdk-prowler@2.30.1.jsii.tgz
cdk_prowler-2.30.1.dist-info/LICENSE
cdk_prowler-2.30.1.dist-info/METADATA
cdk_prowler-2.30.1.dist-info/WHEEL
cdk_prowler-2.30.1.dist-info/top_level.txt
cdk_prowler-2.30.1.dist-info/RECORD
