Metadata-Version: 2.1
Name: cdk-prowler
Version: 2.30.1
Summary: An AWS CDK custom construct for deploying Prowler to your AWS Account. Prowler is a security tool to perform AWS security best practices assessments, audits, incident response, continuous monitoring, hardening and forensics readiness. It contains all CIS controls listed here https://d0.awsstatic.com/whitepapers/compliance/AWS_CIS_Foundations_Benchmark.pdf and more than 100 additional checks that help on GDPR, HIPAA …
Home-page: https://github.com/mmuller88/cdk-prowler
Author: Martin Mueller<damadden88@googlemail.com>
License: Apache-2.0
Project-URL: Source, https://github.com/mmuller88/cdk-prowler
Platform: UNKNOWN
Classifier: Intended Audience :: Developers
Classifier: Operating System :: OS Independent
Classifier: Programming Language :: JavaScript
Classifier: Programming Language :: Python :: 3 :: Only
Classifier: Programming Language :: Python :: 3.7
Classifier: Programming Language :: Python :: 3.8
Classifier: Programming Language :: Python :: 3.9
Classifier: Programming Language :: Python :: 3.10
Classifier: Typing :: Typed
Classifier: Development Status :: 5 - Production/Stable
Classifier: License :: OSI Approved
Requires-Python: ~=3.7
License-File: LICENSE
Requires-Dist: aws-cdk-lib (<3.0.0,>=2.30.0)
Requires-Dist: cdk-iam-floyd (<0.392.0,>=0.391.0)
Requires-Dist: constructs (<11.0.0,>=10.0.5)
Requires-Dist: jsii (<2.0.0,>=1.61.0)
Requires-Dist: publication (>=0.0.3)
